crypto_data_fetcher/__init__.py
crypto_data_fetcher/bases.py
crypto_data_fetcher/data_fetchers.py
crypto_data_fetcher/formatters.py
crypto_data_fetcher/response_models.py
crypto_data_fetcher-1.0.0.dist-info/LICENSE
crypto_data_fetcher-1.0.0.dist-info/METADATA
crypto_data_fetcher-1.0.0.dist-info/WHEEL
crypto_data_fetcher-1.0.0.dist-info/top_level.txt
crypto_data_fetcher-1.0.0.dist-info/RECORD
