Metadata-Version: 2.1
Name: crypto-data-fetcher
Version: 1.0.0
Summary: Utilities for fetching Crypto Coin data
Home-page: https://gitlab.com/satyamsoni2211/cryptodatafetcher
Author: Satyam Soni
Author-email: satyamsoni@hotmail.co.uk
Maintainer: Satyam Soni
Maintainer-email: satyamsoni@hotmail.co.uk
License: UNKNOWN
Keywords: Bitcoin,crypto,crypto currency,dodge coin,coin
Platform: Platform Independent
License-File: LICENSE
Requires-Dist: aiohttp (==3.7.4)
Provides-Extra: dev
Requires-Dist: sphinx ; extra == 'dev'
Requires-Dist: sphinx-rtd-theme (==0.5.2) ; extra == 'dev'
Requires-Dist: sphinx-markdown-builder ; extra == 'dev'
